{"_type":"export","__export_format":4,"__export_date":"2023-06-13T09:21:47.560Z","__export_source":"insomnia.desktop.app:v2023.2.2","resources":[{"_id":"req_0ff44bd176bb467aa6ac6fc03b862621","parentId":"fld_8cb95a9d8ac54afba03c41068e0ee7ce","modified":1686646647219,"created":1685359278368,"url":"{{ _.base }}/api/toia_user","name":"Add User","description":"Creates a user account","method":"POST","body":{"mimeType":"multipart/form-data","params":[{"id":"pair_dcc765dc80254fb78b379eaa69313f0a","name":"first_name","value":"{% faker 'name', '', '', '', '', '', '', '', '', '', '', '', '', '', '', '', '', '', 'firstName', '', '', '', '', '', '', '', 'en' %}","description":""},{"id":"pair_6b8dc09211444d3ba2fc11bf1b547373","name":"last_name","value":"{% faker 'name', '', '', '', '', '', '', '', '', '', '', '', '', '', '', '', '', '', 'lastName', '', '', '', '', '', '', '', 'en' %}","description":""},{"id":"pair_aa6c7c458a034517aefb149cfe8a7ecc","name":"language","value":"en","description":""},{"id":"pair_6bb44d4dc737431aab3410b47f07a6c5","name":"password","value":"12345","description":""},{"id":"pair_ac6929717237443e9776ffcf6899d1e8","name":"email","value":"{% faker 'internet', '', '', '', '', '', '', '', '', '', '', '', '', '', 'exampleEmail', '', '', '', '', '', '', '', '', '', 'noun', '', 'en' %}","description":""},{"id":"pair_9da9107c01774b6b99f9a17069eb7abd","name":"profile_pic","value":"{% faker 'image', '', '', '', '', '', '', '', '', '', '', '', '', 'dataUri', '', '', '', '', '', '', '', '', '', '', '', '', 'en' %}","description":"","type":"file","fileName":"/Users/bishnu/Downloads/photo-1579353977828-2a4eab540b9a.jpeg","disabled":false,"multiline":true}]},"parameters":[],"headers":[{"name":"Content-Type","value":"multipart/form-data"}],"authentication":{},"metaSortKey":-1686313680173,"isPrivate":false,"settingStoreCookies":true,"settingSendCookies":true,"settingDisableRenderRequestBody":false,"settingEncodeUrl":true,"settingRebuildPath":true,"settingFollowRedirects":"global","_type":"request"},{"_id":"fld_8cb95a9d8ac54afba03c41068e0ee7ce","parentId":"wrk_d41b347eb6264626b2c033b9f2689f6a","modified":1686646868455,"created":1686646636571,"name":"User","description":"","environment":{},"environmentPropertyOrder":null,"metaSortKey":-1686646789026.5,"_type":"request_group"},{"_id":"wrk_d41b347eb6264626b2c033b9f2689f6a","parentId":null,"modified":1685358357761,"created":1685358333086,"name":"TOIA API V2","description":"","scope":"design","_type":"workspace"},{"_id":"req_c393fd717b084675b989c421e945e2eb","parentId":"fld_8cb95a9d8ac54afba03c41068e0ee7ce","modified":1686646650882,"created":1685528574498,"url":"{{ _.base }}/api/login","name":"Login","description":"Logs in a user, returns the token as a response.","method":"POST","body":{"mimeType":"application/json","text":"{\n\t\"email\":\"aaaaaaaaaaaaaa\",\n\t\"password\":\"123452\"\n}"},"parameters":[],"headers":[{"name":"Content-Type","value":"application/json"}],"authentication":{},"metaSortKey":-1686313680123,"isPrivate":false,"settingStoreCookies":true,"settingSendCookies":true,"settingDisableRenderRequestBody":false,"settingEncodeUrl":true,"settingRebuildPath":true,"settingFollowRedirects":"global","_type":"request"},{"_id":"req_25573508030d44b4a170b55825dd6bbe","parentId":"fld_8cb95a9d8ac54afba03c41068e0ee7ce","modified":1686646641730,"created":1686313224404,"url":"{{ _.base }}/api/toia_user","name":"Get User Info","description":"Returns the information about the logged in user.\n\n```\n{\n\t\"data\": {\n\t\t\"email\": \"example@example.com\",\n\t\t\"first_name\": \"FirstName\",\n\t\t\"id\": 1,\n\t\t\"language\": \"en\",\n\t\t\"last_name\": \"LastName\"\n\t}\n}\n```","method":"GET","body":{},"parameters":[],"headers":[],"authentication":{"type":"bearer","token":"{{ _.JWT_TOKEN }}"},"metaSortKey":-1686313680223,"isPrivate":false,"settingStoreCookies":true,"settingSendCookies":true,"settingDisableRenderRequestBody":false,"settingEncodeUrl":true,"settingRebuildPath":true,"settingFollowRedirects":"global","_type":"request"},{"_id":"req_c369ee61fc584e2b856d2c1597c646b0","parentId":"fld_8cb95a9d8ac54afba03c41068e0ee7ce","modified":1686646639815,"created":1686313680273,"url":"{{ _.base }}/api/toia_user/stats","name":"Get User Stats","description":"Returns stats about a user: number of streams, total number of videos, and total duration of all videos.\nExample response:\n```\n{\n\t\"data\": {\n\t\t\"totalStreamCounts\": 2,\n\t\t\"totalVideoDuration\": \"6\",\n\t\t\"totalVideosCount\": 1\n\t}\n}\n```","method":"GET","body":{},"parameters":[],"headers":[],"authentication":{"type":"bearer","token":"{{ _.JWT_TOKEN }}"},"metaSortKey":-1686313680273,"isPrivate":false,"settingStoreCookies":true,"settingSendCookies":true,"settingDisableRenderRequestBody":false,"settingEncodeUrl":true,"settingRebuildPath":true,"settingFollowRedirects":"global","_type":"request"},{"_id":"req_27aff9476ec84ddaab8f64caf3287608","parentId":"fld_c606260322c747f1a4475a63a2b2294e","modified":1686646666039,"created":1685527318588,"url":"{{ _.base }}/api/stream","name":"Get All Streams","description":"Returns all public streams of all users","method":"GET","body":{},"parameters":[],"headers":[],"authentication":{"type":"bearer","token":"{{ _.JWT_TOKEN }}"},"metaSortKey":-1685527318588,"isPrivate":false,"settingStoreCookies":true,"settingSendCookies":true,"settingDisableRenderRequestBody":false,"settingEncodeUrl":true,"settingRebuildPath":true,"settingFollowRedirects":"global","_type":"request"},{"_id":"fld_c606260322c747f1a4475a63a2b2294e","parentId":"wrk_d41b347eb6264626b2c033b9f2689f6a","modified":1686646882253,"created":1686646661756,"name":"Stream","description":"","environment":{},"environmentPropertyOrder":null,"metaSortKey":-1686646784749.4375,"_type":"request_group"},{"_id":"req_6989b7b469b54fd5b0b7b2cf8c119046","parentId":"fld_c606260322c747f1a4475a63a2b2294e","modified":1686646675135,"created":1685528117704,"url":"{{ _.base }}/api/stream","name":"Create Stream","description":"Creates a new stream for the logged in user","method":"POST","body":{"mimeType":"multipart/form-data","params":[{"id":"pair_aad1a26ee8bd4186976e857be9b69c94","name":"name","value":"asdasd","description":""},{"id":"pair_1a51f32601e04ca0a2b67f978333e0f9","name":"private","value":"false","description":"","disabled":false},{"id":"pair_0165ce7eb19f40e1ae4f1a8336907155","name":"stream_pic","value":"","description":"","type":"file","fileName":"/Users/bishnu/Downloads/photo-1579353977828-2a4eab540b9a.jpeg"}]},"parameters":[],"headers":[{"name":"Content-Type","value":"multipart/form-data","id":"pair_34448a063db4465a965d8f87661ed365"}],"authentication":{"type":"bearer","token":"{{ _.JWT_TOKEN }}"},"metaSortKey":-1685527318488,"isPrivate":false,"settingStoreCookies":true,"settingSendCookies":true,"settingDisableRenderRequestBody":false,"settingEncodeUrl":true,"settingRebuildPath":true,"settingFollowRedirects":"global","_type":"request"},{"_id":"req_045b31fbfb704033b5bf66299e64f94c","parentId":"fld_c606260322c747f1a4475a63a2b2294e","modified":1686647881319,"created":1685627284214,"url":"{{ _.base }}/api/toia_user/:user_id/streams","name":"Get User Streams","description":"Returns all streams of logged in user or public streams of any user\n\n```\n{\n\t\"data\": [\n\t\t{\n\t\t\t\"id_stream\": 2,\n\t\t\t\"likes\": 0,\n\t\t\t\"name\": \"Death\",\n\t\t\t\"private\": false,\n\t\t\t\"toia_id\": 9,\n\t\t\t\"views\": 0\n\t\t},\n\t\t{\n\t\t\t\"id_stream\": 16,\n\t\t\t\"likes\": 0,\n\t\t\t\"name\": \"New Stream\",\n\t\t\t\"private\": true,\n\t\t\t\"toia_id\": 9,\n\t\t\t\"views\": 0\n\t\t},\n\t\t{\n\t\t\t\"id_stream\": 17,\n\t\t\t\"likes\": 0,\n\t\t\t\"name\": \"New Stream\",\n\t\t\t\"private\": true,\n\t\t\t\"toia_id\": 9,\n\t\t\t\"views\": 0\n\t\t}\n\t]\n}\n```","method":"GET","body":{},"parameters":[],"headers":[],"authentication":{"type":"bearer","token":"{{ _.JWT_TOKEN }}"},"metaSortKey":-1685527318538,"isPrivate":false,"settingStoreCookies":true,"settingSendCookies":true,"settingDisableRenderRequestBody":false,"settingEncodeUrl":true,"settingRebuildPath":true,"settingFollowRedirects":"global","_type":"request"},{"_id":"req_f92173f344fa44ba9d17c139eca52400","parentId":"fld_c606260322c747f1a4475a63a2b2294e","modified":1686647914627,"created":1685694234828,"url":"{{ _.base }}/api/stream/:stream_id/filler","name":"Get Stream Filler Video","description":"Returns a filler video\n\n```\n{\n\t\"filler_video\": \"Accounts/Peter_1/Videos/Peter_1_256_9d748c98.mp4\"\n}\n```","method":"GET","body":{},"parameters":[],"headers":[],"authentication":{"type":"bearer","token":"{{ _.JWT_TOKEN }}"},"metaSortKey":-1685527318388,"isPrivate":false,"settingStoreCookies":true,"settingSendCookies":true,"settingDisableRenderRequestBody":false,"settingEncodeUrl":true,"settingRebuildPath":true,"settingFollowRedirects":"global","_type":"request"},{"_id":"req_22ee31c90ded475f9afbcd6b430556d8","parentId":"fld_c606260322c747f1a4475a63a2b2294e","modified":1686647897285,"created":1685702833688,"url":"{{ _.base }}/api/stream/:stream_id/next","name":"Get Stream Next Video","description":"Returns the appropriate video given a question\n\n```\n{\n\t\"answer\": \".\",\n\t\"duration_seconds\": 5,\n\t\"id_video\": \"Peter_1_107_2514a8b0.mp4\",\n\t\"url\": \"/Videos/Peter_1_107_2514a8b0.mp4\"\n}\n```","method":"GET","body":{},"parameters":[{"id":"pair_7b71469047ee435dad323fdbb6a4935e","name":"question","value":"Cannot Answer","description":""}],"headers":[],"authentication":{"type":"bearer","token":"{{ _.JWT_TOKEN }}"},"metaSortKey":-1685527318438,"isPrivate":false,"settingStoreCookies":true,"settingSendCookies":true,"settingDisableRenderRequestBody":false,"settingEncodeUrl":true,"settingRebuildPath":true,"settingFollowRedirects":"global","_type":"request"},{"_id":"req_7b06b1d5b29e4785ae0c2d322a9b01ea","parentId":"fld_33245cd97c2a4844a1fd3fe1e949e0e7","modified":1686646737525,"created":1685609344563,"url":"{{ _.base }}/api/question_suggestions","name":"Question Suggestions","description":"Returns a list of suggested questions\n\n```\n{\n\t\"data\": [\n\t\t{\n\t\t\t\"id_question\": 678,\n\t\t\t\"isPending\": true,\n\t\t\t\"priority\": 100,\n\t\t\t\"question\": \"Something hasn't changed!\",\n\t\t\t\"type\": \"answer\"\n\t\t}\n\t]\n}\n```","method":"GET","body":{},"parameters":[],"headers":[],"authentication":{"type":"bearer","token":"{{ _.JWT_TOKEN }}"},"metaSortKey":-1686027718823.5,"isPrivate":false,"settingStoreCookies":true,"settingSendCookies":true,"settingDisableRenderRequestBody":false,"settingEncodeUrl":true,"settingRebuildPath":true,"settingFollowRedirects":"global","_type":"request"},{"_id":"fld_33245cd97c2a4844a1fd3fe1e949e0e7","parentId":"wrk_d41b347eb6264626b2c033b9f2689f6a","modified":1686646880412,"created":1686646724583,"name":"Questions","description":"","environment":{},"environmentPropertyOrder":null,"metaSortKey":-1686646776195.3125,"_type":"request_group"},{"_id":"req_2bdf14d5ce1a4ad183e6530da1a2e130","parentId":"fld_33245cd97c2a4844a1fd3fe1e949e0e7","modified":1686647960487,"created":1685624378276,"url":"{{ _.base }}/api/question_suggestions/:id_question","name":"Delete Question Suggestions","description":"Removes a suggestion","method":"DELETE","body":{},"parameters":[],"headers":[],"authentication":{"type":"bearer","token":"{{ _.JWT_TOKEN }}"},"metaSortKey":-1686027718873.5,"isPrivate":false,"settingStoreCookies":true,"settingSendCookies":true,"settingDisableRenderRequestBody":false,"settingEncodeUrl":true,"settingRebuildPath":true,"settingFollowRedirects":"global","_type":"request"},{"_id":"req_e2b4ff7aab00493b8e411072d2b860e7","parentId":"fld_33245cd97c2a4844a1fd3fe1e949e0e7","modified":1686647976738,"created":1685956612770,"url":"{{ _.base }}/api/stream/:stream_id/smart_questions","name":"Get Smart Questions","description":"Returns a list of \"Smart Suggestions\"\n\n```\n[\n\t\"What is your name?\",\n\t\"Where and when were you born?\",\n\t\"What do you do for a living?\",\n\t\"[Brian] When you first found out that you had Parkinson's, how did it feel in that moment?\\\"\",\n\t\"[Ian] Are you afraid of death?\"\n]\n```","method":"GET","body":{},"parameters":[],"headers":[],"authentication":{"type":"bearer","token":"{{ _.JWT_TOKEN }}"},"metaSortKey":-1686027718736,"isPrivate":false,"settingStoreCookies":true,"settingSendCookies":true,"settingDisableRenderRequestBody":false,"settingEncodeUrl":true,"settingRebuildPath":true,"settingFollowRedirects":"global","_type":"request"},{"_id":"req_2a6f62dd8903419d81db7e4c876c395c","parentId":"fld_33245cd97c2a4844a1fd3fe1e949e0e7","modified":1686646741444,"created":1685963484728,"url":"{{ _.base }}/api/question_suggestions/latest","name":"Get Latest Suggestion","description":"Returns the lastest question suggestion\n\n```\n{\n\t\"question_suggestion\": {\n\t\t\"id_question\": 22,\n\t\t\"question\": \"What do you do?\",\n\t\t\"type\": \"answer\"\n\t}\n}\n```","method":"GET","body":{},"parameters":[],"headers":[],"authentication":{"type":"bearer","token":"{{ _.JWT_TOKEN }}"},"metaSortKey":-1686027718773.5,"isPrivate":false,"settingStoreCookies":true,"settingSendCookies":true,"settingDisableRenderRequestBody":false,"settingEncodeUrl":true,"settingRebuildPath":true,"settingFollowRedirects":"global","_type":"request"},{"_id":"req_0b1e6ac3931d4628b82e1693053a1080","parentId":"fld_33245cd97c2a4844a1fd3fe1e949e0e7","modified":1686646744681,"created":1685968336618,"url":"{{ _.base }}/api/question_suggestions","name":"Save Question Suggestion","description":"Saves a question suggestion\n\n```\n{\n\t\"data\": {\n\t\t\"id_question\": 675,\n\t\t\"priority\": 100,\n\t\t\"question\": \"This is a completely new question\",\n\t\t\"type\": \"answer\"\n\t}\n}\n```","method":"POST","body":{"mimeType":"application/json","text":"{\n\t\"question\": \"This is a completely new question\"\n}"},"parameters":[],"headers":[{"name":"Content-Type","value":"application/json","id":"pair_30b3b547822143cfaec24bed3f50b130"}],"authentication":{"type":"bearer","token":"{{ _.JWT_TOKEN }}"},"metaSortKey":-1686027718723.5,"isPrivate":false,"settingStoreCookies":true,"settingSendCookies":true,"settingDisableRenderRequestBody":false,"settingEncodeUrl":true,"settingRebuildPath":true,"settingFollowRedirects":"global","_type":"request"},{"_id":"req_96e978a47cce4d7f8915afd64b555d4a","parentId":"fld_33245cd97c2a4844a1fd3fe1e949e0e7","modified":1686647952080,"created":1686039206406,"url":"{{ _.base }}/api/question_suggestions/:id_question","name":"Edit Suggestion","description":"Modify a suggested question. At least one field is required\n\n```\n{\n\t\"data\": {\n\t\t\"id_question\": 678,\n\t\t\"priority\": 100,\n\t\t\"question\": \"Something hasn't changed!\",\n\t\t\"type\": \"answer\"\n\t}\n}\n```","method":"PATCH","body":{"mimeType":"application/json","text":"{\n\t\"isPending\":true, \n\t\"new_value\": \"Something hasn't changed!\"\n}"},"parameters":[],"headers":[{"name":"Content-Type","value":"application/json","id":"pair_88eae2e51459468496ef6e071bfbd0bb"}],"authentication":{"type":"bearer","token":"{{ _.JWT_TOKEN }}"},"metaSortKey":-1686027718923.5,"isPrivate":false,"settingStoreCookies":true,"settingSendCookies":true,"settingDisableRenderRequestBody":false,"settingEncodeUrl":true,"settingRebuildPath":true,"settingFollowRedirects":"global","_type":"request"},{"_id":"req_a6a7cc59a6a9480e975322f3e7df6821","parentId":"fld_33245cd97c2a4844a1fd3fe1e949e0e7","modified":1686646784125,"created":1686140958233,"url":"{{ _.base }}/api/toia_user/questions/onboarding","name":"Get Onboarding Questions","description":"Returns a list of onboarding questions\n```\n{\n\t\"data\": [\n\t\t{\n\t\t\t\"id\": 290,\n\t\t\t\"onboarding\": false,\n\t\t\t\"pending\": false,\n\t\t\t\"priority\": 100,\n\t\t\t\"question\": \"[Layla] Is it possible to accept death?\",\n\t\t\t\"suggested_type\": \"answer\",\n\t\t\t\"trigger_suggester\": true\n\t\t},\n\t\t{\n\t\t\t\"id\": 290,\n\t\t\t\"onboarding\": false,\n\t\t\t\"pending\": false,\n\t\t\t\"priority\": 100,\n\t\t\t\"question\": \"[Layla] Is it possible to accept death?\",\n\t\t\t\"suggested_type\": \"answer\",\n\t\t\t\"trigger_suggester\": true\n\t\t}\n\t]\n}\n```","method":"GET","body":{},"parameters":[],"headers":[],"authentication":{"type":"bearer","token":"{{ _.JWT_TOKEN }}"},"metaSortKey":-1686027718748.5,"isPrivate":false,"settingStoreCookies":true,"settingSendCookies":true,"settingDisableRenderRequestBody":false,"settingEncodeUrl":true,"settingRebuildPath":true,"settingFollowRedirects":"global","_type":"request"},{"_id":"req_a97987c15aa640a588920fee4234e2b7","parentId":"fld_33245cd97c2a4844a1fd3fe1e949e0e7","modified":1686646792601,"created":1686230506234,"url":"{{ _.base }}/api/question/answered","name":"Get Answered Questions","description":"Get list of recorded questions for the logged in user\n```\n{\n\t\"data\": [\n\t\t{\n\t\t\t\"id\": 290,\n\t\t\t\"id_video\": \"Peter_1_120_ba4ec838.mp4\",\n\t\t\t\"onboarding\": false,\n\t\t\t\"priority\": 100,\n\t\t\t\"question\": \"[Layla] Is it possible to accept death?\",\n\t\t\t\"suggested_type\": \"answer\",\n\t\t\t\"trigger_suggester\": true,\n\t\t\t\"type\": \"answer\"\n\t\t},\n\t\t{\n\t\t\t\"id\": 290,\n\t\t\t\"id_video\": \"Peter_1_120_ba4ec838.mp4\",\n\t\t\t\"onboarding\": false,\n\t\t\t\"priority\": 100,\n\t\t\t\"question\": \"[Layla] Is it possible to accept death?\",\n\t\t\t\"suggested_type\": \"answer\",\n\t\t\t\"trigger_suggester\": true,\n\t\t\t\"type\": \"answer\"\n\t\t}\n\t]\n}\n```","method":"GET","body":{},"parameters":[],"headers":[],"authentication":{"type":"bearer","token":"{{ _.JWT_TOKEN }}"},"metaSortKey":-1686027718729.75,"isPrivate":false,"settingStoreCookies":true,"settingSendCookies":true,"settingDisableRenderRequestBody":false,"settingEncodeUrl":true,"settingRebuildPath":true,"settingFollowRedirects":"global","_type":"request"},{"_id":"req_a4e430b5b594470ca0e6641d1c1ae515","parentId":"fld_33245cd97c2a4844a1fd3fe1e949e0e7","modified":1686648100210,"created":1686232260359,"url":"{{ _.base }}/api/question/answered","name":"Get Others Answered Questions","description":"Returns the question list for all videos in a stream.\n\n```\n{\n\t\"data\": [\n\t\t{\n\t\t\t\"id\": 10,\n\t\t\t\"id_video\": \"Peter_1_10_fbc0cedc.mp4\",\n\t\t\t\"onboarding\": true,\n\t\t\t\"priority\": 9,\n\t\t\t\"question\": \"Inattentive filler: Cross hands while looking upward or elsewere, looking bored, avoiding eye contact with the camera\",\n\t\t\t\"suggested_type\": \"filler\",\n\t\t\t\"trigger_suggester\": false,\n\t\t\t\"type\": \"filler\"\n\t\t}\n\t]\n}\n```","method":"GET","body":{},"parameters":[{"id":"pair_c37a6e9f968e45c6b5416980d1de5f86","name":"stream_id","value":"1","description":""}],"headers":[],"authentication":{"type":"bearer","token":"{{ _.JWT_TOKEN }}","disabled":false},"metaSortKey":-1686027718673.5,"isPrivate":false,"settingStoreCookies":true,"settingSendCookies":true,"settingDisableRenderRequestBody":false,"settingEncodeUrl":true,"settingRebuildPath":true,"settingFollowRedirects":"global","_type":"request"},{"_id":"req_3fd2cf33152543ea84689a26b46942f9","parentId":"fld_6f312add593645dea4b813a65f28b8cd","modified":1686646767385,"created":1685625429896,"url":"{{ _.base }}/api/video","name":"Get Videos","description":"Returns a list of user's videos\n\n```\n{\n\t\"data\": [\n\t\t{\n\t\t\t\"answer\": \"Hi, I am peter\",\n\t\t\t\"duration_seconds\": 6,\n\t\t\t\"id_video\": \"Peter_1_120_ba4ec838.mp4\",\n\t\t\t\"idx\": 120,\n\t\t\t\"language\": \"EN\",\n\t\t\t\"likes\": 0,\n\t\t\t\"private\": false,\n\t\t\t\"toia_id\": 9,\n\t\t\t\"views\": 0\n\t\t}\n\t]\n}\n```","method":"GET","body":{},"parameters":[],"headers":[],"authentication":{"type":"bearer","token":"{{ _.JWT_TOKEN }}"},"metaSortKey":-1685625429896,"isPrivate":false,"settingStoreCookies":true,"settingSendCookies":true,"settingDisableRenderRequestBody":false,"settingEncodeUrl":true,"settingRebuildPath":true,"settingFollowRedirects":"global","_type":"request"},{"_id":"fld_6f312add593645dea4b813a65f28b8cd","parentId":"wrk_d41b347eb6264626b2c033b9f2689f6a","modified":1686646876325,"created":1686646754810,"name":"Recordings","description":"","environment":{},"environmentPropertyOrder":null,"metaSortKey":-1686646780472.375,"_type":"request_group"},{"_id":"req_456df8a0b4d44377bf174dc9511b0de3","parentId":"fld_6f312add593645dea4b813a65f28b8cd","modified":1686647934541,"created":1685692149980,"url":"{{ _.base }}/api/video/:video_id","name":"Get Particular Video","description":"Returns info about a certain video\n\n```\n{\n\t\"data\": {\n\t\t\"answer\": \"[Peter] Hi I'm Peter\",\n\t\t\"duration_seconds\": 4,\n\t\t\"id_video\": \"Peter_1_102_9e173890.mp4\",\n\t\t\"idx\": 102,\n\t\t\"language\": \"EN\",\n\t\t\"likes\": 0,\n\t\t\"private\": false,\n\t\t\"toia_id\": 1,\n\t\t\"videoURL\": \"/Peter_9/Videos/Peter_1_102_9e173890.mp4\",\n\t\t\"views\": 0\n\t}\n}\n```","method":"GET","body":{},"parameters":[],"headers":[],"authentication":{"type":"bearer","token":"{{ _.JWT_TOKEN }}"},"metaSortKey":-1685625429846,"isPrivate":false,"settingStoreCookies":true,"settingSendCookies":true,"settingDisableRenderRequestBody":false,"settingEncodeUrl":true,"settingRebuildPath":true,"settingFollowRedirects":"global","_type":"request"},{"_id":"req_de35cd7748434e98892ff7531f370990","parentId":"fld_6f312add593645dea4b813a65f28b8cd","modified":1686646788267,"created":1686223443741,"url":"{{ _.base }}/api/video_question_stream","name":"Delete a video + question pair","description":"Removes a recorded video\n\n```\n{\n\t\"removedEntries\": 2\n}\n```","method":"DELETE","body":{"mimeType":"application/json","text":"{\n\t\"question_id\":\"613\",\n\t\"video_id\":\"Peter_1_227_34e7d74a.mp4\"\n}"},"parameters":[],"headers":[{"name":"Content-Type","value":"application/json","id":"pair_943d60d463024455ade808d89211eb7a"}],"authentication":{"type":"bearer","token":"{{ _.JWT_TOKEN }}"},"metaSortKey":-1685625429871,"isPrivate":false,"settingStoreCookies":true,"settingSendCookies":true,"settingDisableRenderRequestBody":false,"settingEncodeUrl":true,"settingRebuildPath":true,"settingFollowRedirects":"global","_type":"request"},{"_id":"req_419c5bf63f2e4117b8bfe81197e6ca53","parentId":"fld_0c1579634a2f4ea980f143ee133bbf96","modified":1686648061057,"created":1686568389442,"url":"{{ _.base }}/api/player_feedback","name":"Save Feedback","description":"Saves the rating (feedback)\n\n```\n{\n\t\"data\": {\n\t\t\"id\": 1,\n\t\t\"question\": \"Test\",\n\t\t\"rating\": 4,\n\t\t\"video_id\": \"Peter_1_72_2f14d1d1.mp4\"\n\t}\n}\n```","method":"POST","body":{"mimeType":"application/json","text":"{\n\t\"video_id\":\"Peter_1_72_2f14d1d1.mp4\",\n\t\"question\":\"Test\",\n\t\"rating\":4\n}"},"parameters":[],"headers":[{"name":"Content-Type","value":"application/json","id":"pair_fdf6ffbd149b44a785309ee77bb29763"}],"authentication":{"type":"bearer","token":"{{ _.JWT_TOKEN }}"},"metaSortKey":-1686270327630.25,"isPrivate":false,"settingStoreCookies":true,"settingSendCookies":true,"settingDisableRenderRequestBody":false,"settingEncodeUrl":true,"settingRebuildPath":true,"settingFollowRedirects":"global","_type":"request"},{"_id":"fld_0c1579634a2f4ea980f143ee133bbf96","parentId":"wrk_d41b347eb6264626b2c033b9f2689f6a","modified":1686646872183,"created":1686646823243,"name":"Misc","description":"","environment":{},"environmentPropertyOrder":null,"metaSortKey":-1686646771918.25,"_type":"request_group"},{"_id":"env_108058da1463dbe3a14126ceb8d33cb74518f671","parentId":"wrk_d41b347eb6264626b2c033b9f2689f6a","modified":1686646998996,"created":1685358333090,"name":"Base Environment","data":{"base":"http://localhost:4000","JWT_TOKEN":"AUTH_TOKEN"},"dataPropertyOrder":{"&":["base","JWT_TOKEN"]},"color":null,"isPrivate":false,"metaSortKey":1685358333090,"_type":"environment"},{"_id":"jar_108058da1463dbe3a14126ceb8d33cb74518f671","parentId":"wrk_d41b347eb6264626b2c033b9f2689f6a","modified":1686643781039,"created":1685358333092,"name":"Default Jar","cookies":[],"_type":"cookie_jar"},{"_id":"spc_dbc7bd1cb743439fbdf6227fdad0d3bc","parentId":"wrk_d41b347eb6264626b2c033b9f2689f6a","modified":1686570160366,"created":1685358333087,"fileName":"TOIA API V2","contents":"","contentType":"yaml","_type":"api_spec"}]}