[
	{
		"question": "Attentive filler video: Record yourself touching your hair/head/face staring at the camera (think making eye contact with a user interacting with your avatar)",
		"type": "filler",
		"priority": 0,
		"trigger_suggester": false
	},
	{
		"question": "Attentive filler: Nod/shake head to show you are listening, and keep staring at the camere (make eye contact)",
		"type": "filler",
		"priority": 1,
		"trigger_suggester": false
	},
	{
		"question": "Attentive filler: Smile and blink eyes while looking towards the camera (make eye contact) for about 10 seconds",
		"type": "filler",
		"priority": 2,
		"trigger_suggester": false
	},
	{
		"question": "Attentive filler: Lean slightly forward with your elbows on the table and your hands together on your chin as if you were attentive to the camera",
		"type": "filler",
		"priority": 3,
		"trigger_suggester": false
	},
	{
		"question": "Attentive filler: Cross hands while looking forward into the camera",
		"type": "filler",
		"priority": 4,
		"trigger_suggester": false
	},
	{
		"question": "Inattentive filler video: Now record again yourself touching your hair/head/face, but don't look at the camera. Look elsewhere (don't make eye contact)",
		"type": "filler",
		"priority": 5,
		"trigger_suggester": false
	},
	{
		"question": "Inattentive filler: Do not nod/shake head and look elsewhere from the camera. Show you are engageing with somebody else in the room, do not stare at the camera (avoid eye contact)",
		"type": "filler",
		"priority": 6,
		"trigger_suggester": false
	},
	{
		"question": "Inattentive filler: Look downward, do not stare at the camera (avoid eye contact) for about 10 seconds",
		"type": "filler",
		"priority": 7,
		"trigger_suggester": false
	},
	{
		"question": "Inattentive filler: Lean slightly backwards, like trying to relax, gaze around and never look at the camera (avoid eye contact)",
		"type": "filler",
		"priority": 8,
		"trigger_suggester": false
	},
	{
		"question": "Inattentive filler: Cross hands while looking upward or elsewere, looking bored, avoiding eye contact with the camera",
		"type": "filler",
		"priority": 9,
		"trigger_suggester": false
	},
	{
		"question": "Say: I don't have an answer to that right now.",
		"type": "no-answer",
		"priority": 10,
		"trigger_suggester": false
	},
	{
		"question": "Say: Sorry, I didn't record answers to that question.",
		"type": "no-answer",
		"priority": 11,
		"trigger_suggester": false
	},
	{
		"question": "Say: Can you try rephrasing the question?",
		"type": "no-answer",
		"priority": 12,
		"trigger_suggester": false
	},
	{
		"question": "Record a greeting (e.g., hello, hi)",
		"type": "greeting",
		"priority": 13,
		"trigger_suggester": false
	},
	{
		"question": "Record a goodbye (or end of conversation sentence)",
		"type": "exit",
		"priority": 14,
		"trigger_suggester": false
	},
	{
		"question": "Record yourself saying Yes. You cann add questions for this answer later.",
		"type": "y/n-answer",
		"priority": 15,
		"trigger_suggester": false
	},
	{
		"question": "Record yourself saying No. You can add questions for this answer later.",
		"type": "y/n-answer",
		"priority": 16,
		"trigger_suggester": false
	},
	{
        "question": "ما اسمك؟",
        "type": "answer",
        "priority": 17,
        "trigger_suggester": true
    },
    {
        "question": "اين و متى ولدت؟",
        "type": "answer",
        "priority": 18,
        "trigger_suggester": true
    },
    {
        "question": "ماذا تعمل لكسب عيشك؟",
        "type": "answer",
        "priority": 19,
        "trigger_suggester": true
    },
    {
        "question": "ما هو تخصصك ولماذا اخترته؟",
        "type": "answer",
        "priority": 20,
        "trigger_suggester": true
    },
    {
        "question": "كيف كانت تجربتك الأكاديمية حتى الآن؟",
        "type": "answer",
        "priority": 21,
        "trigger_suggester": true
    },
    {
        "question": "هل شاركت في أي مشاريع بحثية أو دورات تدريبية؟",
        "type": "answer",
        "priority": 22,
        "trigger_suggester": true
    },
    {
        "question": "ما هو أكثر صفك تحديًا ، وكيف تغلبت عليه؟",
        "type": "answer",
        "priority": 23,
        "trigger_suggester": true
    },
    {
        "question": "ما هو فصلك المفضل ولماذا؟",
        "type": "answer",
        "priority": 24,
        "trigger_suggester": true
    },
    {
        "question": "هل شاركت في أي أنشطة أو نوادي غير منهجية؟",
        "type": "answer",
        "priority": 25,
        "trigger_suggester": true
    },
    {
        "question": "ما المناصب القيادية التي شغلتها في الجامعة؟",
        "type": "answer",
        "priority": 26,
        "trigger_suggester": true
    },
    {
        "question": "هل درست بالخارج إذا كان الأمر كذلك ، فأين وماذا تعلمت من التجربة؟",
        "type": "answer",
        "priority": 27,
        "trigger_suggester": true
    },
    {
        "question": "كيف غيرتك الجامعة كشخص؟",
        "type": "answer",
        "priority": 28,
        "trigger_suggester": true
    },
    {
        "question": "ما هي خطتك بعد التخرج؟",
        "type": "answer",
        "priority": 29,
        "trigger_suggester": true
    },
    {
        "question": "ما هو شعورك تجاه الالتحاق بسوق العمل أو كلية الدراسات العليا؟",
        "type": "answer",
        "priority": 30,
        "trigger_suggester": true
    },
    {
        "question": "ما هي نقاط القوة والضعف لديك؟",
        "type": "answer",
        "priority": 31,
        "trigger_suggester": true
    },
    {
        "question": "هل سبق لك أن تعرضت لفشل أو انتكاسة؟ كيف تتعاملون مع ذلك؟",
        "type": "answer",
        "priority": 32,
        "trigger_suggester": true
    },
    {
        "question": "ما الذي يحفزك على النجاح؟",
        "type": "answer",
        "priority": 33,
        "trigger_suggester": true
    },
    {
        "question": "ما رأيك هو أعظم إنجاز لك في الجامعة؟",
        "type": "answer",
        "priority": 34,
        "trigger_suggester": true
    },
    {
        "question": "ما أكثر شيء تفتخر به في مسيرتك الجامعية؟",
        "type": "answer",
        "priority": 35,
        "trigger_suggester": true
    },
    {
        "question": "هل أجريت أي علاقات أو صداقات دائمة في الجامعة؟",
        "type": "answer",
        "priority": 36,
        "trigger_suggester": true
    },
    {
        "question": "ما هو الشيء الذي كنت تتمنى أن تكون قد عرفته قبل الالتحاق بالجامعة؟",
        "type": "answer",
        "priority": 37,
        "trigger_suggester": true
    },
    {
        "question": "ما هي النصيحة التي تقدمها للطلاب الجدد في الجامعة؟",
        "type": "answer",
        "priority": 38,
        "trigger_suggester": true
    },
    {
        "question": "ما هي أكبر عقبة واجهتها خلال مسيرتك الجامعية؟",
        "type": "answer",
        "priority": 39,
        "trigger_suggester": true
    },
    {
        "question": "كيف كنت تدير وقتك خلال الجامعة؟",
        "type": "answer",
        "priority": 40,
        "trigger_suggester": true
    },
    {
        "question": "ما هي عادات الدراسة الأفضل بالنسبة لك؟",
        "type": "answer",
        "priority": 41,
        "trigger_suggester": true
    },
    {
        "question": "هل سبق لك أن غيرت مسار تخصصك أو مهنتك؟ إذا كان الأمر كذلك لماذا؟",
        "type": "answer",
        "priority": 42,
        "trigger_suggester": true
    },
    {
        "question": "ما هي برأيك أكبر المشكلات التي تواجه طلاب الجامعة اليوم؟",
        "type": "answer",
        "priority": 43,
        "trigger_suggester": true
    },
    {
        "question": "كيف تحافظ على دوافعك وتركيزك على أهدافك؟",
        "type": "answer",
        "priority": 44,
        "trigger_suggester": true
    },
    {
        "question": "كيف توازن بين المسؤوليات الأكاديمية والحياة الشخصية والعلاقات؟",
        "type": "answer",
        "priority": 45,
        "trigger_suggester": true
    },
    {
        "question": "كيف تكيفت مع التغييرات والتحديات التي أحدثها جائحة COVID-19؟",
        "type": "answer",
        "priority": 46,
        "trigger_suggester": true
    },
    {
        "question": "ما هي بعض المهارات القيمة التي اكتسبتها في الجامعة؟",
        "type": "answer",
        "priority": 47,
        "trigger_suggester": true
    },
    {
        "question": "ما هو الشيء الذي كنت تتمنى لو فعلته بشكل مختلف في الجامعة؟",
        "type": "answer",
        "priority": 48,
        "trigger_suggester": true
    },
    {
        "question": "كيف تغيرت قيمك ومعتقداتك منذ أن بدأت الجامعة؟",
        "type": "answer",
        "priority": 49,
        "trigger_suggester": true
    },
    {
        "question": "ما هو تأثير تجربتك الجامعية على نظرتك للعالم؟",
        "type": "answer",
        "priority": 50,
        "trigger_suggester": true
    },
    {
        "question": "ما هي الذكرى المفضلة لديك من الجامعة؟",
        "type": "answer",
        "priority": 51,
        "trigger_suggester": true
    },
    {
        "question": "ما هو أهم درس تعلمته في الجامعة؟",
        "type": "answer",
        "priority": 52,
        "trigger_suggester": true
    },
    {
        "question": "كيف تتعامل مع الإجهاد والضغط؟",
        "type": "answer",
        "priority": 53,
        "trigger_suggester": true
    },
    {
        "question": "ما هي خططك لرد الجميل لمجتمعك أو مجتمعك؟",
        "type": "answer",
        "priority": 54,
        "trigger_suggester": true
    },
    {
        "question": "ما هي الهوايات أو الاهتمامات التي لديك خارج الأكاديميين؟",
        "type": "answer",
        "priority": 55,
        "trigger_suggester": true
    },
    {
        "question": "كيف طورت مهاراتك القيادية في الجامعة؟",
        "type": "answer",
        "priority": 56,
        "trigger_suggester": true
    },
    {
        "question": "هل شاركت في أي خدمة مجتمعية أو عمل تطوعي؟",
        "type": "answer",
        "priority": 57,
        "trigger_suggester": true
    },
    {
        "question": "ما هو أكبر تحد شخصي واجهته في الجامعة؟",
        "type": "answer",
        "priority": 58,
        "trigger_suggester": true
    },
    {
        "question": "ما رأيك في أهم صفات النجاح في حياتك المهنية المستقبلية؟",
        "type": "answer",
        "priority": 59,
        "trigger_suggester": true
    },
    {
        "question": "ما هو الشيء الذي ترغب في تحقيقه في السنوات الخمس المقبلة؟",
        "type": "answer",
        "priority": 60,
        "trigger_suggester": true
    },
    {
        "question": "ما الذي يحفزك لتكون ناجحًا؟",
        "type": "answer",
        "priority": 61,
        "trigger_suggester": true
    },
    {
        "question": "ما هي أهدافك المهنية طويلة المدى؟",
        "type": "answer",
        "priority": 62,
        "trigger_suggester": true
    },
    {
        "question": "كيف تخطط لتحقيق أهدافك طويلة المدى؟",
        "type": "answer",
        "priority": 63,
        "trigger_suggester": true
    },
    {
        "question": "كيف طورت مهاراتك في التفكير النقدي في الجامعة؟",
        "type": "answer",
        "priority": 64,
        "trigger_suggester": true
    },
    {
        "question": "ما هي أكثر التجارب ذات المغزى التي مررت بها في الجامعة؟",
        "type": "answer",
        "priority": 65,
        "trigger_suggester": true
    },
    {
        "question": "كيف أثرت على مجتمعك الجامعي؟",
        "type": "answer",
        "priority": 66,
        "trigger_suggester": true
    },
    {
        "question": "كيف طورت مهارات الاتصال الخاصة بك في الجامعة؟",
        "type": "answer",
        "priority": 67,
        "trigger_suggester": true
    },
    {
        "question": "هل كان لديك أي خبرات إرشادية في الجامعة؟ إذا كان الأمر كذلك ، كيف أثروا عليك؟",
        "type": "answer",
        "priority": 68,
        "trigger_suggester": true
    },
    {
        "question": "ماذا تعلمت عن نفسك أثناء وجودك في الجامعة؟",
        "type": "answer",
        "priority": 69,
        "trigger_suggester": true
    },
    {
        "question": "ما هو مشروعك أو مهمتك المفضلة في الجامعة ، ولماذا؟",
        "type": "answer",
        "priority": 70,
        "trigger_suggester": true
    },
    {
        "question": "ما هو الدور الذي لعبته التكنولوجيا في تجربتك الجامعية؟",
        "type": "answer",
        "priority": 71,
        "trigger_suggester": true
    },
    {
        "question": "كيف تعاملت مع الأساتذة أو زملاء الدراسة الصعبة أو الصعبة؟",
        "type": "answer",
        "priority": 72,
        "trigger_suggester": true
    },
    {
        "question": "كيف يمكنك البقاء على اطلاع دائم بالأحداث الجارية والأخبار في مجال دراستك؟",
        "type": "answer",
        "priority": 73,
        "trigger_suggester": true
    },
    {
        "question": "ما هي بعض أكبر المخاطر التي واجهتها في الجامعة ، وكيف أتت ثمارها؟",
        "type": "answer",
        "priority": 74,
        "trigger_suggester": true
    },
    {
        "question": "كيف طورت مهاراتك في العمل الجماعي والتعاون في الجامعة؟",
        "type": "answer",
        "priority": 75,
        "trigger_suggester": true
    },
    {
        "question": "هل لديك أي تجارب مع مبادرات التنوع والشمول في الحرم الجامعي؟ إذا كان الأمر كذلك ، كيف أثروا على نظرتك للعالم؟",
        "type": "answer",
        "priority": 76,
        "trigger_suggester": true
    },
    {
        "question": "كيف طورت مهاراتك في حل المشكلات في الجامعة؟",
        "type": "answer",
        "priority": 77,
        "trigger_suggester": true
    },
    {
        "question": "ما هي أكبر التضحيات التي قدمتها في السعي وراء تعليمك الجامعي؟",
        "type": "answer",
        "priority": 78,
        "trigger_suggester": true
    }
]
